main.py
iflow_mcp_crypto_projects_mcp-0.1.1.dist-info/licenses/LICENSE
iflow_mcp_crypto_projects_mcp-0.1.1.dist-info/METADATA
iflow_mcp_crypto_projects_mcp-0.1.1.dist-info/WHEEL
iflow_mcp_crypto_projects_mcp-0.1.1.dist-info/entry_points.txt
iflow_mcp_crypto_projects_mcp-0.1.1.dist-info/top_level.txt
iflow_mcp_crypto_projects_mcp-0.1.1.dist-info/RECORD
