Metadata-Version: 2.4
Name: iflow-mcp_crypto-projects-mcp
Version: 0.1.1
Summary: An MCP server providing cryptocurrency project data to AI agents
Requires-Python: >=3.10
License-File: LICENSE
Requires-Dist: mcp[cli]>=1.7.1
Requires-Dist: httpx>=0.25.0
Dynamic: license-file
